{
  "spawns": [
    321,
    -1,
    321,
    321,
    321,
    400,
    321,
    321,
    321,
    321,
    321,
    400,
    83,
    400,
    321,
    321,
    322,
    323,
    325,
    -1,
    -1,
    -1,
    400,
    85,
    82,
    83,
    85,
    321,
    -1,
    321,
    321,
    325,
    322,
    -1,
    82,
    83,
    324,
    321,
    321,
    400,
    400,
    82,
    84,
    83,
    83,
    -1,
    321,
    321,
    323,
    82,
    83,
    400,
    14,
    321,
    325,
    20,
    321,
    321,
    323,
    322,
    83
  ],

  "blocks": [

    {
      "rect":         [ 1, 20, 56, 1 ],
      "enemies":      [ 0, 1, 2, 3, 4, 5 ],
      "respawn":      [ ],
      "clear":        [ 1, 2, 3, 4 ],
      "vip":          [ ],
      "exceptional":  [ ],
      "text":         "We are almost out of the Alderan mines.",
      "countdown":    0
    },

    {
      "rect":         [ 30, 60, 56, 22 ],
      "enemies":      [ 6, 7, 8, 9, 10, 11, 12, 13 ],
      "respawn":      [ ],
      "clear":        [ 6, 7, 8, 9, 10 ],
      "vip":          [ ],
      "exceptional":  [ 12 ],
      "text":         "",
      "countdown":    0
    },

    {
      "rect":         [ 56, 60, 87, 40 ],
      "enemies":      [ 14, 15, 16, 17, 18, 22, 23, 24, 25 ],
      "respawn":      [ ],
      "clear":        [ 14, 15, 16, 17, 18 ],
      "vip":          [ ],
      "exceptional":  [ 23, 24, 25 ],
      "text":         "",
      "countdown":    0
    },

    {
      "rect":         [ 110, 60, 141, 30 ],
      "enemies":      [ 26, 27, 28, 29, 30, 31, 32, 33, 34, 35, 36, 37, 38, 39, 40 ],
      "respawn":      [ ],
      "clear":        [ 27, 28, 29, 30, 31, 32, 33, 36, 37, 38 ],
      "vip":          [ ],
      "exceptional":  [ 26, 34, 35 ],
      "text":         "",
      "countdown":    0
    },

    {
      "rect":         [ 165, 60, 185, 40 ],
      "enemies":      [ 41, 42, 43, 44, 45, 46, 47, 48, 49, 50, 51 ],
      "respawn":      [ ],
      "clear":        [ 46, 47, 48 ],
      "vip":          [ ],
      "exceptional":  [ 41, 42, 43, 44, 49, 50 ],
      "text":         "",
      "countdown":    0
    },

    {
      "rect":         [ 155, 89, 185, 60 ],
      "enemies":      [ 53, 54, 55, 56, 57, 58 ],
      "respawn":      [ ],
      "clear":        [ 55 ],
      "vip":          [ 55 ],
      "exceptional":  [ 60 ],
      "text":         "Destroy the Golem of Steel and mark your exit out of the mines!",
      "countdown":    0
    }

  ]
}